{
  "version": "5",
  "dialect": "mysql",
  "id": "6ee346bf-5ba1-49f3-9a8e-029dfdb48302",
  "prevId": "00000000-0000-0000-0000-000000000000",
  "tables": {
    "Comments": {
      "name": "Comments",
      "columns": {
        "id": {
          "name": "id",
          "type": "bigint",
          "primaryKey": false,
          "notNull": true,
          "autoincrement": true
        },
        "content": {
          "name": "content",
          "type": "text",
          "primaryKey": false,
          "notNull": false,
          "autoincrement": false
        },
        "post_id": {
          "name": "post_id",
          "type": "bigint",
          "primaryKey": false,
          "notNull": true,
          "autoincrement": false
        },
        "author_id": {
          "name": "author_id",
          "type": "int",
          "primaryKey": false,
          "notNull": true,
          "autoincrement": false
        },
        "created_at": {
          "name": "created_at",
          "type": "timestamp",
          "primaryKey": false,
          "notNull": false,
          "autoincrement": false,
          "default": "(now())"
        },
        "updated_at": {
          "name": "updated_at",
          "type": "timestamp",
          "primaryKey": false,
          "notNull": false,
          "autoincrement": false,
          "onUpdate": true
        }
      },
      "indexes": {},
      "foreignKeys": {},
      "compositePrimaryKeys": {
        "Comments_id": {
          "name": "Comments_id",
          "columns": [
            "id"
          ]
        }
      },
      "uniqueConstraints": {}
    },
    "Posts": {
      "name": "Posts",
      "columns": {
        "id": {
          "name": "id",
          "type": "bigint",
          "primaryKey": false,
          "notNull": true,
          "autoincrement": true
        },
        "title": {
          "name": "title",
          "type": "varchar(255)",
          "primaryKey": false,
          "notNull": false,
          "autoincrement": false,
          "default": "'No title'"
        },
        "content": {
          "name": "content",
          "type": "longtext",
          "primaryKey": false,
          "notNull": false,
          "autoincrement": false
        },
        "summary": {
          "name": "summary",
          "type": "varchar(255)",
          "primaryKey": false,
          "notNull": false,
          "autoincrement": false
        },
        "post_id": {
          "name": "post_id",
          "type": "varchar(255)",
          "primaryKey": false,
          "notNull": false,
          "autoincrement": false
        },
        "slug": {
          "name": "slug",
          "type": "varchar(255)",
          "primaryKey": false,
          "notNull": true,
          "autoincrement": false
        },
        "status": {
          "name": "status",
          "type": "enum('draft','published','deleted')",
          "primaryKey": false,
          "notNull": false,
          "autoincrement": false,
          "default": "'draft'"
        },
        "author_id": {
          "name": "author_id",
          "type": "int",
          "primaryKey": false,
          "notNull": true,
          "autoincrement": false
        },
        "created_at": {
          "name": "created_at",
          "type": "timestamp",
          "primaryKey": false,
          "notNull": false,
          "autoincrement": false,
          "default": "(now())"
        },
        "updated_at": {
          "name": "updated_at",
          "type": "timestamp",
          "primaryKey": false,
          "notNull": false,
          "autoincrement": false,
          "onUpdate": true
        }
      },
      "indexes": {},
      "foreignKeys": {},
      "compositePrimaryKeys": {
        "Posts_id": {
          "name": "Posts_id",
          "columns": [
            "id"
          ]
        }
      },
      "uniqueConstraints": {}
    },
    "Replies": {
      "name": "Replies",
      "columns": {
        "id": {
          "name": "id",
          "type": "bigint",
          "primaryKey": false,
          "notNull": true,
          "autoincrement": true
        },
        "content": {
          "name": "content",
          "type": "text",
          "primaryKey": false,
          "notNull": false,
          "autoincrement": false
        },
        "comment_id": {
          "name": "comment_id",
          "type": "bigint",
          "primaryKey": false,
          "notNull": true,
          "autoincrement": false
        },
        "author_id": {
          "name": "author_id",
          "type": "int",
          "primaryKey": false,
          "notNull": true,
          "autoincrement": false
        },
        "created_at": {
          "name": "created_at",
          "type": "timestamp",
          "primaryKey": false,
          "notNull": false,
          "autoincrement": false,
          "default": "(now())"
        },
        "updated_at": {
          "name": "updated_at",
          "type": "timestamp",
          "primaryKey": false,
          "notNull": false,
          "autoincrement": false,
          "onUpdate": true
        }
      },
      "indexes": {},
      "foreignKeys": {},
      "compositePrimaryKeys": {
        "Replies_id": {
          "name": "Replies_id",
          "columns": [
            "id"
          ]
        }
      },
      "uniqueConstraints": {}
    },
    "Users": {
      "name": "Users",
      "columns": {
        "id": {
          "name": "id",
          "type": "int",
          "primaryKey": false,
          "notNull": true,
          "autoincrement": true
        },
        "name": {
          "name": "name",
          "type": "varchar(120)",
          "primaryKey": false,
          "notNull": true,
          "autoincrement": false
        },
        "email": {
          "name": "email",
          "type": "varchar(255)",
          "primaryKey": false,
          "notNull": true,
          "autoincrement": false
        },
        "password": {
          "name": "password",
          "type": "varchar(255)",
          "primaryKey": false,
          "notNull": false,
          "autoincrement": false
        },
        "bio": {
          "name": "bio",
          "type": "varchar(255)",
          "primaryKey": false,
          "notNull": false,
          "autoincrement": false
        },
        "username": {
          "name": "username",
          "type": "varchar(255)",
          "primaryKey": false,
          "notNull": false,
          "autoincrement": false
        },
        "avatar": {
          "name": "avatar",
          "type": "varchar(255)",
          "primaryKey": false,
          "notNull": false,
          "autoincrement": false
        },
        "role": {
          "name": "role",
          "type": "enum('admin','editor','user')",
          "primaryKey": false,
          "notNull": false,
          "autoincrement": false,
          "default": "'user'"
        },
        "created_at": {
          "name": "created_at",
          "type": "timestamp",
          "primaryKey": false,
          "notNull": false,
          "autoincrement": false,
          "default": "(now())"
        },
        "updated_at": {
          "name": "updated_at",
          "type": "timestamp",
          "primaryKey": false,
          "notNull": false,
          "autoincrement": false,
          "onUpdate": true
        }
      },
      "indexes": {},
      "foreignKeys": {},
      "compositePrimaryKeys": {
        "Users_id": {
          "name": "Users_id",
          "columns": [
            "id"
          ]
        }
      },
      "uniqueConstraints": {}
    }
  },
  "_meta": {
    "schemas": {},
    "tables": {},
    "columns": {}
  },
  "internal": {
    "tables": {},
    "indexes": {}
  }
}